setup.py
jiaqiscore/__init__.py
jiaqiscore/get_score.py
jiaqiscore.egg-info/PKG-INFO
jiaqiscore.egg-info/SOURCES.txt
jiaqiscore.egg-info/dependency_links.txt
jiaqiscore.egg-info/requires.txt
jiaqiscore.egg-info/top_level.txt