Metadata-Version: 1.0
Name: jiaqiscore
Version: 2.2.4
Summary: This is ustc-iscr score package
Home-page: https://github.com/WolverineQin/jiaqiscore
Author: qjqqjq
Author-email: 1102692995@qq.com
License: MIT Licence
Keywords: pip,jiaqiscore,featureextraction
Platform: any
